model_pipeline_pypi/__init__.py
model_pipeline_pypi/model_pipeline_pypi.py
PEC_project_Diego_Benavent-0.1.1.dist-info/METADATA
PEC_project_Diego_Benavent-0.1.1.dist-info/WHEEL
PEC_project_Diego_Benavent-0.1.1.dist-info/top_level.txt
PEC_project_Diego_Benavent-0.1.1.dist-info/RECORD
