Metadata-Version: 2.1
Name: PEC-project-Diego-Benavent
Version: 0.1.1
Summary: A training pipeline for a model to predict if a passenger survived the Titanic
Author: Diego Benavent
Requires-Dist: scikit-learn (==1.2.2)
Requires-Dist: pandas (==2.0.2)
Requires-Dist: flask (==2.3.2)
Requires-Dist: requests (==2.31.0)
